README.md
setup.cfg
setup.py
cartago/PBXCarthageScriptBuildPhase.py
cartago/__init__.py
cartago/cartago.py
cartago.egg-info/PKG-INFO
cartago.egg-info/SOURCES.txt
cartago.egg-info/dependency_links.txt
cartago.egg-info/entry_points.txt
cartago.egg-info/requires.txt
cartago.egg-info/top_level.txt