Metadata-Version: 1.1
Name: cartago
Version: 0.3
Summary: An automated framework installer using carthage
Home-page: https://github.com/HelmMobile/Cartago
Author: HELM S.C.P.
Author-email: pypi@helm.cat
License: UNKNOWN
Download-URL: https://github.com/HelmMobile/Cartago/archive/0.3.tar.gz
Keywords: carthage,swift,xcode,ios,framework,script,xcode project
Platform: UNKNOWN
